{
  "Serilog": {
    "MinimumLevel": {
      "Default": "Error",
      "Override": {
        "Skoruba": "Information"
      }
    },
    "WriteTo": [
      {
        "Name": "Console"
      },
      {
        "Name": "File",
        "Args": {
          "path": "Log/skoruba_admin.txt",
          "rollingInterval": "Day"
        }
      },
      {
        "Name": "MSSqlServer",
        "Args": {
          "connectionString": "Data Source=sqlserver;Initial Catalog=IdentityServer4Admin.DockerDevelopment;Persist Security Info=False;User ID=sa;Password=Cl4v32up3r23gur4*;MultipleActiveResultSets=True;Encrypt=True;TrustServerCertificate=True;Connection Timeout=30;",
          "tableName": "Log",
          "columnOptionsSection": {
            "addStandardColumns": [ "LogEvent" ],
            "removeStandardColumns": [ "Properties" ]
          }
        }
      }
    ]
  }
}